{
"免嗅":"1",
"分类url":"https://www.dlidl.com/list/{cateId}--------{catePg}---.html",
"分类": "国产剧$guocanju#香港剧$xianggangju#欧美剧$oumeiju#海外剧$haiwaiju#台湾剧$taiwanju#日韩剧$rihanju#电影$dianying#动漫$dongman#综艺$zongyi",
"数组": "class=\"pic-list&&</ul>",
"副标题":"class=\"titles\">&&</span>",
"状态":"<div class=\"col-md-wide-8 col-xs-wide-65 video-info&&</div>",
"导演": "导演：&&</div",
"主演": "主演：&&</div",
"简介": "txt-hid txt-hid2>&&</p>",
"线路数组": "class=\"play-title&&</div>",
"线路标题": ">&&</a>",
"播放数组":"class=\"play-list clearfix&&</div>",
"播放标题":">&&</a>",
"搜索url": "https://www.54pv.com/vodsearch/{wd}-----------.html",
"搜索模式": "1",
"搜索数组": "class=\"module-search-item&&</div>",
"年份": "2007-2022",
"筛选": "1"
}